{
  "projetos": [
    {
      "id": "1",
      "nome": "Tracker Campos Net"
    }
  ],
  "tarefas": [
    {
      "id": "5566",
      "duracaoEmSegundos": 4,
      "descricao": "Vuex e Composition API",
      "projeto": {
        "id": "1",
        "nome": "Tracker Campos Net"
      }
    },
    {
      "id": "8bdd",
      "duracaoEmSegundos": 2,
      "descricao": "",
      "projeto": {
        "id": "1",
        "nome": "Tracker Campos Net"
      }
    },
    {
      "id": "8d5d",
      "duracaoEmSegundos": 1,
      "descricao": ""
    }
  ]
}